alibabacloud_credentials/__init__.py
alibabacloud_credentials/client.py
alibabacloud_credentials/credentials.py
alibabacloud_credentials/exceptions.py
alibabacloud_credentials/models.py
alibabacloud_credentials/providers.py
alibabacloud_credentials/utils/__init__.py
alibabacloud_credentials/utils/auth_constant.py
alibabacloud_credentials/utils/auth_util.py
alibabacloud_credentials/utils/parameter_helper.py
alcloud_credentials-0.3.2.dist-info/METADATA
alcloud_credentials-0.3.2.dist-info/WHEEL
alcloud_credentials-0.3.2.dist-info/top_level.txt
alcloud_credentials-0.3.2.dist-info/RECORD
